{
  "settingsReloadIntervalMinutes": 1,
  "fullscreen": true,
  "autoStart": false,
  "lazyLoadTabs": false,
  "websites": [
    {
      "url": "https://docs.google.com/presentation/d/1dSOCx7tkmmppeeXESa1f37aBiiHhNpugiA33cp-LXhE/edit?ts=5cf7728e#slide=id.p1",
      "duration": 10,
      "tabReloadIntervalSeconds": 15
    },
    {
      "url": "https://docs.google.com/presentation/d/1KRSvtN-yEPrQ1p12ra4f1vyos2S9CBUPhaRd897koWc/edit?ts=5cf77284#slide=id.g587c059b89_0_0",
      "duration": 10,
      "tabReloadIntervalSeconds": 15
    },
    {
      "url": "https://one.solvay.com/fr/index.html",
      "duration": 10,
      "tabReloadIntervalSeconds": 300
    } 
  ]
}
